{
  "head_steps": [],
  "hyperparameters": {
    "batch_size": 4096,
    "cifar_root": "/Users/gunale/works/silifen-works/SLN/data/cifar10",
    "datasets": "CIFAR10",
    "feature_dim": 512,
    "features": "handcraft",
    "fit_per_class": 1000,
    "head_lr": 0.2,
    "mnist_root": "/Users/gunale/works/silifen-works/haoran_idea/data",
    "n_classes": 10,
    "output": "experiments/results_pure_dgm_cifar10_handcraft_aug_mps.json",
    "seeds": "0,1",
    "shots": "500,1000,2000",
    "support_aug": "hflip,shift2r,shift2l,shift2d,shift2u",
    "support_pool_per_class": 2000,
    "temperature": 0.07,
    "test_per_class": 500
  },
  "knn_k": [],
  "protocol": "Pure no-backprop DGM-style read/write benchmark. Features are raw pixels or fixed unsupervised/random projections; support examples are stored in nonparametric DGM memory, while linear heads are gradient baselines on the same fixed features.",
  "ridge": [
    0.1,
    1.0,
    10.0
  ],
  "rows": [
    {
      "accuracy": 0.5317999720573425,
      "dataset": "CIFAR10",
      "feature": "handcraft",
      "feature_dim": 1200,
      "memory_items": 30000,
      "method": "PureDGM-ridge0.1",
      "nll": 2.088857412338257,
      "seconds": 0.02675183303654194,
      "seed": 0,
      "shots": 500
    },
    {
      "accuracy": 0.5351999998092651,
      "dataset": "CIFAR10",
      "feature": "handcraft",
      "feature_dim": 1200,
      "memory_items": 30000,
      "method": "PureDGM-ridge1",
      "nll": 2.094034433364868,
      "seconds": 0.02403612481430173,
      "seed": 0,
      "shots": 500
    },
    {
      "accuracy": 0.5329999923706055,
      "dataset": "CIFAR10",
      "feature": "handcraft",
      "feature_dim": 1200,
      "memory_items": 30000,
      "method": "PureDGM-ridge10",
      "nll": 2.115682601928711,
      "seconds": 0.024075540946796536,
      "seed": 0,
      "shots": 500
    },
    {
      "accuracy": 0.33480000495910645,
      "dataset": "CIFAR10",
      "feature": "handcraft",
      "feature_dim": 1200,
      "memory_items": 10,
      "method": "PureDGM-prototype",
      "nll": 2.688544511795044,
      "seconds": 0.005801209015771747,
      "seed": 0,
      "shots": 500
    },
    {
      "accuracy": 0.5249999761581421,
      "dataset": "CIFAR10",
      "feature": "handcraft",
      "feature_dim": 1200,
      "memory_items": 30000,
      "method": "PureDGM-ridge0.1",
      "nll": 2.092249631881714,
      "seconds": 0.023937332909554243,
      "seed": 1,
      "shots": 500
    },
    {
      "accuracy": 0.5289999842643738,
      "dataset": "CIFAR10",
      "feature": "handcraft",
      "feature_dim": 1200,
      "memory_items": 30000,
      "method": "PureDGM-ridge1",
      "nll": 2.0971081256866455,
      "seconds": 0.023422333877533674,
      "seed": 1,
      "shots": 500
    },
    {
      "accuracy": 0.5281999707221985,
      "dataset": "CIFAR10",
      "feature": "handcraft",
      "feature_dim": 1200,
      "memory_items": 30000,
      "method": "PureDGM-ridge10",
      "nll": 2.118427276611328,
      "seconds": 0.023882291978225112,
      "seed": 1,
      "shots": 500
    },
    {
      "accuracy": 0.3246000111103058,
      "dataset": "CIFAR10",
      "feature": "handcraft",
      "feature_dim": 1200,
      "memory_items": 10,
      "method": "PureDGM-prototype",
      "nll": 2.729457139968872,
      "seconds": 0.006365499924868345,
      "seed": 1,
      "shots": 500
    },
    {
      "accuracy": 0.5371999740600586,
      "dataset": "CIFAR10",
      "feature": "handcraft",
      "feature_dim": 1200,
      "memory_items": 60000,
      "method": "PureDGM-ridge0.1",
      "nll": 2.088675022125244,
      "seconds": 0.06124183302745223,
      "seed": 0,
      "shots": 1000
    },
    {
      "accuracy": 0.5415999889373779,
      "dataset": "CIFAR10",
      "feature": "handcraft",
      "feature_dim": 1200,
      "memory_items": 60000,
      "method": "PureDGM-ridge1",
      "nll": 2.0918195247650146,
      "seconds": 0.043242250103503466,
      "seed": 0,
      "shots": 1000
    },
    {
      "accuracy": 0.5386000275611877,
      "dataset": "CIFAR10",
      "feature": "handcraft",
      "feature_dim": 1200,
      "memory_items": 60000,
      "method": "PureDGM-ridge10",
      "nll": 2.106475353240967,
      "seconds": 0.04515037499368191,
      "seed": 0,
      "shots": 1000
    },
    {
      "accuracy": 0.3361999988555908,
      "dataset": "CIFAR10",
      "feature": "handcraft",
      "feature_dim": 1200,
      "memory_items": 10,
      "method": "PureDGM-prototype",
      "nll": 2.6711928844451904,
      "seconds": 0.014023208059370518,
      "seed": 0,
      "shots": 1000
    },
    {
      "accuracy": 0.5375999808311462,
      "dataset": "CIFAR10",
      "feature": "handcraft",
      "feature_dim": 1200,
      "memory_items": 60000,
      "method": "PureDGM-ridge0.1",
      "nll": 2.090935230255127,
      "seconds": 0.042170500149950385,
      "seed": 1,
      "shots": 1000
    },
    {
      "accuracy": 0.5397999882698059,
      "dataset": "CIFAR10",
      "feature": "handcraft",
      "feature_dim": 1200,
      "memory_items": 60000,
      "method": "PureDGM-ridge1",
      "nll": 2.0940165519714355,
      "seconds": 0.042589208809658885,
      "seed": 1,
      "shots": 1000
    },
    {
      "accuracy": 0.5378000140190125,
      "dataset": "CIFAR10",
      "feature": "handcraft",
      "feature_dim": 1200,
      "memory_items": 60000,
      "method": "PureDGM-ridge10",
      "nll": 2.108611822128296,
      "seconds": 0.04331529210321605,
      "seed": 1,
      "shots": 1000
    },
    {
      "accuracy": 0.32899999618530273,
      "dataset": "CIFAR10",
      "feature": "handcraft",
      "feature_dim": 1200,
      "memory_items": 10,
      "method": "PureDGM-prototype",
      "nll": 2.707827568054199,
      "seconds": 0.013069083215668797,
      "seed": 1,
      "shots": 1000
    },
    {
      "accuracy": 0.5483999848365784,
      "dataset": "CIFAR10",
      "feature": "handcraft",
      "feature_dim": 1200,
      "memory_items": 120000,
      "method": "PureDGM-ridge0.1",
      "nll": 2.088796615600586,
      "seconds": 0.07979787490330637,
      "seed": 0,
      "shots": 2000
    },
    {
      "accuracy": 0.550000011920929,
      "dataset": "CIFAR10",
      "feature": "handcraft",
      "feature_dim": 1200,
      "memory_items": 120000,
      "method": "PureDGM-ridge1",
      "nll": 2.0906970500946045,
      "seconds": 0.0823617500718683,
      "seed": 0,
      "shots": 2000
    },
    {
      "accuracy": 0.5511999726295471,
      "dataset": "CIFAR10",
      "feature": "handcraft",
      "feature_dim": 1200,
      "memory_items": 120000,
      "method": "PureDGM-ridge10",
      "nll": 2.1004998683929443,
      "seconds": 0.07962320814840496,
      "seed": 0,
      "shots": 2000
    },
    {
      "accuracy": 0.335999995470047,
      "dataset": "CIFAR10",
      "feature": "handcraft",
      "feature_dim": 1200,
      "memory_items": 10,
      "method": "PureDGM-prototype",
      "nll": 2.689303398132324,
      "seconds": 0.025372291915118694,
      "seed": 0,
      "shots": 2000
    },
    {
      "accuracy": 0.5483999848365784,
      "dataset": "CIFAR10",
      "feature": "handcraft",
      "feature_dim": 1200,
      "memory_items": 120000,
      "method": "PureDGM-ridge0.1",
      "nll": 2.088796854019165,
      "seconds": 0.07986491685733199,
      "seed": 1,
      "shots": 2000
    },
    {
      "accuracy": 0.550000011920929,
      "dataset": "CIFAR10",
      "feature": "handcraft",
      "feature_dim": 1200,
      "memory_items": 120000,
      "method": "PureDGM-ridge1",
      "nll": 2.0906975269317627,
      "seconds": 0.07830845797434449,
      "seed": 1,
      "shots": 2000
    },
    {
      "accuracy": 0.5511999726295471,
      "dataset": "CIFAR10",
      "feature": "handcraft",
      "feature_dim": 1200,
      "memory_items": 120000,
      "method": "PureDGM-ridge10",
      "nll": 2.1004998683929443,
      "seconds": 0.08015241613611579,
      "seed": 1,
      "shots": 2000
    },
    {
      "accuracy": 0.335999995470047,
      "dataset": "CIFAR10",
      "feature": "handcraft",
      "feature_dim": 1200,
      "memory_items": 10,
      "method": "PureDGM-prototype",
      "nll": 2.689303398132324,
      "seconds": 0.02607120806351304,
      "seed": 1,
      "shots": 2000
    }
  ],
  "summary": {
    "CIFAR10/handcraft/1000_shot/PureDGM-prototype": {
      "accuracy_mean": 0.3325999975204468,
      "accuracy_std": 0.003600001335144043,
      "feature_dim_mean": 1200.0,
      "feature_dim_std": 0.0,
      "memory_items_mean": 10.0,
      "memory_items_std": 0.0,
      "nll_mean": 2.689510226249695,
      "nll_std": 0.018317341804504395,
      "seconds_mean": 0.013546145637519658,
      "seconds_std": 0.0004770624218508601
    },
    "CIFAR10/handcraft/1000_shot/PureDGM-ridge0.1": {
      "accuracy_mean": 0.5373999774456024,
      "accuracy_std": 0.00020000338554382324,
      "feature_dim_mean": 1200.0,
      "feature_dim_std": 0.0,
      "memory_items_mean": 60000.0,
      "memory_items_std": 0.0,
      "nll_mean": 2.0898051261901855,
      "nll_std": 0.0011301040649414062,
      "seconds_mean": 0.05170616658870131,
      "seconds_std": 0.009535666438750923
    },
    "CIFAR10/handcraft/1000_shot/PureDGM-ridge1": {
      "accuracy_mean": 0.5406999886035919,
      "accuracy_std": 0.0009000003337860107,
      "feature_dim_mean": 1200.0,
      "feature_dim_std": 0.0,
      "memory_items_mean": 60000.0,
      "memory_items_std": 0.0,
      "nll_mean": 2.092918038368225,
      "nll_std": 0.0010985136032104492,
      "seconds_mean": 0.042915729456581175,
      "seconds_std": 0.0003265206469222903
    },
    "CIFAR10/handcraft/1000_shot/PureDGM-ridge10": {
      "accuracy_mean": 0.5382000207901001,
      "accuracy_std": 0.0004000067710876465,
      "feature_dim_mean": 1200.0,
      "feature_dim_std": 0.0,
      "memory_items_mean": 60000.0,
      "memory_items_std": 0.0,
      "nll_mean": 2.1075435876846313,
      "nll_std": 0.0010682344436645508,
      "seconds_mean": 0.04423283354844898,
      "seconds_std": 0.0009175414452329278
    },
    "CIFAR10/handcraft/2000_shot/PureDGM-prototype": {
      "accuracy_mean": 0.335999995470047,
      "accuracy_std": 0.0,
      "feature_dim_mean": 1200.0,
      "feature_dim_std": 0.0,
      "memory_items_mean": 10.0,
      "memory_items_std": 0.0,
      "nll_mean": 2.689303398132324,
      "nll_std": 0.0,
      "seconds_mean": 0.025721749989315867,
      "seconds_std": 0.0003494580741971731
    },
    "CIFAR10/handcraft/2000_shot/PureDGM-ridge0.1": {
      "accuracy_mean": 0.5483999848365784,
      "accuracy_std": 0.0,
      "feature_dim_mean": 1200.0,
      "feature_dim_std": 0.0,
      "memory_items_mean": 120000.0,
      "memory_items_std": 0.0,
      "nll_mean": 2.0887967348098755,
      "nll_std": 1.1920928955078125e-07,
      "seconds_mean": 0.07983139588031918,
      "seconds_std": 3.352097701281309e-05
    },
    "CIFAR10/handcraft/2000_shot/PureDGM-ridge1": {
      "accuracy_mean": 0.550000011920929,
      "accuracy_std": 0.0,
      "feature_dim_mean": 1200.0,
      "feature_dim_std": 0.0,
      "memory_items_mean": 120000.0,
      "memory_items_std": 0.0,
      "nll_mean": 2.0906972885131836,
      "nll_std": 2.384185791015625e-07,
      "seconds_mean": 0.0803351040231064,
      "seconds_std": 0.0020266460487619042
    },
    "CIFAR10/handcraft/2000_shot/PureDGM-ridge10": {
      "accuracy_mean": 0.5511999726295471,
      "accuracy_std": 0.0,
      "feature_dim_mean": 1200.0,
      "feature_dim_std": 0.0,
      "memory_items_mean": 120000.0,
      "memory_items_std": 0.0,
      "nll_mean": 2.1004998683929443,
      "nll_std": 0.0,
      "seconds_mean": 0.07988781214226037,
      "seconds_std": 0.0002646039938554168
    },
    "CIFAR10/handcraft/500_shot/PureDGM-prototype": {
      "accuracy_mean": 0.3297000080347061,
      "accuracy_std": 0.00509999692440033,
      "feature_dim_mean": 1200.0,
      "feature_dim_std": 0.0,
      "memory_items_mean": 10.0,
      "memory_items_std": 0.0,
      "nll_mean": 2.709000825881958,
      "nll_std": 0.020456314086914062,
      "seconds_mean": 0.006083354470320046,
      "seconds_std": 0.0002821454545482993
    },
    "CIFAR10/handcraft/500_shot/PureDGM-ridge0.1": {
      "accuracy_mean": 0.5283999741077423,
      "accuracy_std": 0.0033999979496002197,
      "feature_dim_mean": 1200.0,
      "feature_dim_std": 0.0,
      "memory_items_mean": 30000.0,
      "memory_items_std": 0.0,
      "nll_mean": 2.0905535221099854,
      "nll_std": 0.0016961097717285156,
      "seconds_mean": 0.02534458297304809,
      "seconds_std": 0.0014072500634938478
    },
    "CIFAR10/handcraft/500_shot/PureDGM-ridge1": {
      "accuracy_mean": 0.5320999920368195,
      "accuracy_std": 0.0031000077724456787,
      "feature_dim_mean": 1200.0,
      "feature_dim_std": 0.0,
      "memory_items_mean": 30000.0,
      "memory_items_std": 0.0,
      "nll_mean": 2.095571279525757,
      "nll_std": 0.0015368461608886719,
      "seconds_mean": 0.0237292293459177,
      "seconds_std": 0.0003068954683840275
    },
    "CIFAR10/handcraft/500_shot/PureDGM-ridge10": {
      "accuracy_mean": 0.530599981546402,
      "accuracy_std": 0.002400010824203491,
      "feature_dim_mean": 1200.0,
      "feature_dim_std": 0.0,
      "memory_items_mean": 30000.0,
      "memory_items_std": 0.0,
      "nll_mean": 2.1170549392700195,
      "nll_std": 0.0013723373413085938,
      "seconds_mean": 0.023978916462510824,
      "seconds_std": 9.662448428571224e-05
    }
  }
}